ovos_config/__init__.py
ovos_config/__main__.py
ovos_config/config.py
ovos_config/locale.py
ovos_config/locations.py
ovos_config/meta.py
ovos_config/models.py
ovos_config/mycroft.conf
ovos_config/ovos.py
ovos_config/utils.py
ovos_config/version.py
ovos_config/recommends/base/ca-es.conf
ovos_config/recommends/base/da-dk.conf
ovos_config/recommends/base/de-de.conf
ovos_config/recommends/base/en-au.conf
ovos_config/recommends/base/en-gb.conf
ovos_config/recommends/base/en-us.conf
ovos_config/recommends/base/es-es.conf
ovos_config/recommends/base/eu-es.conf
ovos_config/recommends/base/fr-fr.conf
ovos_config/recommends/base/gl-es.conf
ovos_config/recommends/base/it-it.conf
ovos_config/recommends/base/nl-nl.conf
ovos_config/recommends/base/pt-br.conf
ovos_config/recommends/base/pt-pt.conf
ovos_config/recommends/gpu/ca-es.conf
ovos_config/recommends/gpu/da-dk.conf
ovos_config/recommends/gpu/de-de.conf
ovos_config/recommends/gpu/en-us.conf
ovos_config/recommends/gpu/es-es.conf
ovos_config/recommends/gpu/eu-es.conf
ovos_config/recommends/gpu/fr-fr.conf
ovos_config/recommends/gpu/gl-es.conf
ovos_config/recommends/gpu/it-it.conf
ovos_config/recommends/gpu/nl-nl.conf
ovos_config/recommends/gpu/pt-pt.conf
ovos_config/recommends/offline_female/ca-ba.conf
ovos_config/recommends/offline_female/ca-es.conf
ovos_config/recommends/offline_female/ca-nw.conf
ovos_config/recommends/offline_female/ca-va.conf
ovos_config/recommends/offline_female/de-de.conf
ovos_config/recommends/offline_female/en-gb.conf
ovos_config/recommends/offline_female/en-us.conf
ovos_config/recommends/offline_female/es-es.conf
ovos_config/recommends/offline_female/eu-es.conf
ovos_config/recommends/offline_female/fr-fr.conf
ovos_config/recommends/offline_female/gl-es.conf
ovos_config/recommends/offline_female/it-it.conf
ovos_config/recommends/offline_female/nl-nl.conf
ovos_config/recommends/offline_male/ca-ba.conf
ovos_config/recommends/offline_male/ca-es.conf
ovos_config/recommends/offline_male/ca-nw.conf
ovos_config-2.1.1.dist-info/LICENSE
ovos_config-2.1.1.dist-info/METADATA
ovos_config-2.1.1.dist-info/WHEEL
ovos_config-2.1.1.dist-info/entry_points.txt
ovos_config-2.1.1.dist-info/top_level.txt
ovos_config-2.1.1.dist-info/RECORD
