Metadata-Version: 2.1
Name: ovos-config
Version: 2.1.1
Summary: ovos-core configuration module
Home-page: https://github.com/OpenVoiceOS/ovos-config
License: Apache-2.0
License-File: LICENSE
Requires-Dist: PyYAML<7.0.0,>=5.4.0
Requires-Dist: combo-lock~=0.3
Requires-Dist: python-dateutil~=2.9
Requires-Dist: ovos-utils<1.0.0,>=0.0.37
Requires-Dist: rich-click~=1.6
